pandas_audio_methods/__init__.py
pandas_audio_methods/core.py
pandas_audio_methods/dask.py
pandas_audio_methods/huggingface.py
pandas_audio_methods-0.0.1.dist-info/LICENSE
pandas_audio_methods-0.0.1.dist-info/METADATA
pandas_audio_methods-0.0.1.dist-info/WHEEL
pandas_audio_methods-0.0.1.dist-info/RECORD
