Metadata-Version: 2.1
Name: pandas-audio-methods
Version: 0.0.1
Summary: Audio methods for pandas dataframes using soundfile
License: Apache-2.0
Author: Quentin Lhoest
Requires-Python: >=3.10
Classifier: License :: OSI Approved :: Apache Software License
Classifier: Programming Language :: Python :: 3
Classifier: Programming Language :: Python :: 3.10
Classifier: Programming Language :: Python :: 3.11
Classifier: Programming Language :: Python :: 3.12
Classifier: Programming Language :: Python :: 3.13
Requires-Dist: numpy (>=2.0)
Requires-Dist: pandas (>=2.0)
Requires-Dist: pyarrow (>=0.18)
Requires-Dist: soundfile (>=0.12)
